README.md
setup.py
msqlib.egg-info/PKG-INFO
msqlib.egg-info/SOURCES.txt
msqlib.egg-info/dependency_links.txt
msqlib.egg-info/entry_points.txt
msqlib.egg-info/requires.txt
msqlib.egg-info/top_level.txt
qlib/__init__.py
qlib/config.py
qlib/log.py
qlib/utils.py
qlib/version.py
qlib/contrib/__init__.py
qlib/contrib/evaluate.py
qlib/contrib/evaluate_portfolio.py
qlib/contrib/backtest/__init__.py
qlib/contrib/backtest/account.py
qlib/contrib/backtest/backtest.py
qlib/contrib/backtest/exchange.py
qlib/contrib/backtest/order.py
qlib/contrib/backtest/position.py
qlib/contrib/backtest/profit_attribution.py
qlib/contrib/backtest/report.py
qlib/contrib/estimator/__init__.py
qlib/contrib/estimator/config.py
qlib/contrib/estimator/estimator.py
qlib/contrib/estimator/fetcher.py
qlib/contrib/estimator/handler.py
qlib/contrib/estimator/launcher.py
qlib/contrib/estimator/processor.py
qlib/contrib/estimator/trainer.py
qlib/contrib/model/__init__.py
qlib/contrib/model/base.py
qlib/contrib/model/gbdt.py
qlib/contrib/model/pytorch_nn.py
qlib/contrib/online/__init__.py
qlib/contrib/online/executor.py
qlib/contrib/online/manager.py
qlib/contrib/online/online_model.py
qlib/contrib/online/operator.py
qlib/contrib/online/user.py
qlib/contrib/online/utils.py
qlib/contrib/report/__init__.py
qlib/contrib/report/graph.py
qlib/contrib/report/analysis_model/__init__.py
qlib/contrib/report/analysis_model/analysis_model_performance.py
qlib/contrib/report/analysis_position/__init__.py
qlib/contrib/report/analysis_position/cumulative_return.py
qlib/contrib/report/analysis_position/parse_position.py
qlib/contrib/report/analysis_position/rank_label.py
qlib/contrib/report/analysis_position/report.py
qlib/contrib/report/analysis_position/risk_analysis.py
qlib/contrib/report/analysis_position/score_ic.py
qlib/contrib/strategy/__init__.py
qlib/contrib/strategy/cost_control.py
qlib/contrib/strategy/order_generator.py
qlib/contrib/strategy/strategy.py
qlib/contrib/tuner/__init__.py
qlib/contrib/tuner/config.py
qlib/contrib/tuner/launcher.py
qlib/contrib/tuner/pipeline.py
qlib/contrib/tuner/space.py
qlib/contrib/tuner/tuner.py
qlib/data/__init__.py
qlib/data/base.py
qlib/data/cache.py
